<?xml version="1.0"?>
<scr:component xmlns:scr="http://www.osgi.org/xmlns/scr/v1.1.0" name="com.liferay.ide.upgrade.problems.core.internal.liferay71.MovedUploadServletRequestPortalProperties">
   <property name="file.extensions" value="properties"/>
   <property name="problem.title" value="Moved Upload Servlet Request Portal Properties to OSGi Configuration"/>
   <property name="problem.summary" value="The Upload Servlet Request properties have been moved from the portal.properties file and Server Administration"/>
   <property name="problem.tickets" value="LPS-69102"/>
   <property name="problem.section" value="#moved-upload-servlet-request-portal-properties"/>
   <property name="version" value="7.1"/>
   <service>
      <provide interface="com.liferay.ide.upgrade.problems.core.FileMigrator"/>
   </service>
   <implementation class="com.liferay.ide.upgrade.problems.core.internal.liferay71.MovedUploadServletRequestPortalProperties"/>
</scr:component>