<?xml version="1.0"?>
<scr:component xmlns:scr="http://www.osgi.org/xmlns/scr/v1.1.0" name="com.liferay.ide.upgrade.problems.core.internal.liferay73.RemovedLiferayFrontendCardsTreeviewTags">
   <property name="file.extensions" value="jsp,jspf"/>
   <property name="problem.title" value="Removed liferay-frontend:cards-treeview Tag"/>
   <property name="problem.section" value="#removed-the-liferay-frontend:cards-treeview-tag"/>
   <property name="problem.summary" value="Removed liferay-frontend:cards-treeview Tag"/>
   <property name="problem.tickets" value="LPS-106899"/>
   <property name="problem.version" value="7.3"/>
   <property name="version" value="7.3"/>
   <service>
      <provide interface="com.liferay.ide.upgrade.problems.core.FileMigrator"/>
   </service>
   <implementation class="com.liferay.ide.upgrade.problems.core.internal.liferay73.RemovedLiferayFrontendCardsTreeviewTags"/>
</scr:component>