<?xml version="1.0" encoding="UTF-8"?>
<scr:component name="com.liferay.ide.upgrade.problems.core.internal.liferay71.MovedOrganizationTypeProperties" xmlns:scr="http://www.osgi.org/xmlns/scr/v1.1.0">
	<property name="file.extensions" value="properties" />
	<property name="problem.title" value="Moved Organization Type Properties to OSGi Configuration" />
	<property name="problem.summary" value="The organization type properties have been moved from portal.properties" />
	<property name="problem.tickets" value="LPS-77183" />
	<property name="problem.section" value="#moved-organization-type-properties" />
	<property name="implName" value="MovedOrganizationTypeProperties" />
	<property name="version" value="7.1" />
	<service>
		<provide interface="com.liferay.ide.upgrade.problems.core.FileMigrator" />
	</service>
	<implementation class="com.liferay.ide.upgrade.problems.core.internal.liferay71.MovedOrganizationTypeProperties" />
</scr:component>