<?xml version="1.0"?>
<scr:component xmlns:scr="http://www.osgi.org/xmlns/scr/v1.1.0" name="com.liferay.ide.upgrade.problems.core.internal.liferay73.MovedBootstrapCacheProperties">
   <property name="file.extensions" value="properties"/>
   <property name="problem.title" value="Removed cache bootstrap feature"/>
   <property name="problem.summary" value="Three bootstrap cache properties have been moved from portal.properties to an OSGi configuration."/>
   <property name="problem.tickets" value="LPS-96563"/>
   <property name="problem.section" value="#moved-bootstrap-cache-properties"/>
   <property name="version" value="7.3"/>
   <service>
      <provide interface="com.liferay.ide.upgrade.problems.core.FileMigrator"/>
   </service>
   <implementation class="com.liferay.ide.upgrade.problems.core.internal.liferay73.MovedBootstrapCacheProperties"/>
</scr:component>