<?xml version="1.0" encoding="UTF-8"?>
<site>
   <description url="http://www.liferay.com/pt/community/liferay-projects/liferay-ide/overview">
     Liferay IDE is the official set of eclipse plugins for supporting Liferay Portal development platorm.
   </description>
   <feature url="features/com.liferay.ide.eclipse.tools_0.0.0.qualifer.jar" id="com.liferay.ide.eclipse.tools" version="0.0.0">
      <category name="Liferay Tools"/>
   </feature>
   <category-def name="Liferay Tools" label="Liferay Tools">
      <description>
         Liferay IDE is the official set of eclipse plugins for supporting Liferay Portal development platorm.
      </description>
   </category-def>
</site>
